README.md
setup.py
admincli/__init__.py
admincli/api.py
admincli/cli.py
admincli/help.py
admincli/parse.py
admincli/utils.py
ddladmin.egg-info/PKG-INFO
ddladmin.egg-info/SOURCES.txt
ddladmin.egg-info/dependency_links.txt
ddladmin.egg-info/entry_points.txt
ddladmin.egg-info/requires.txt
ddladmin.egg-info/top_level.txt