Metadata-Version: 2.1
Name: ddladmin
Version: 1.0.0
Summary: cli for distributed deep learning admin portal
Home-page: UNKNOWN
Author: Shen Wang
Author-email: nedlitex0053@gmail.com
License: UNKNOWN
Platform: UNKNOWN
Classifier: Programming Language :: Python :: 3
Classifier: License :: OSI Approved :: MIT License
Classifier: Operating System :: OS Independent
